factoria/__ini__.py
factoria/base.py
factoria/decorators.py
factoria/exceptions.py
factoria-0.1.0.dist-info/METADATA
factoria-0.1.0.dist-info/WHEEL
factoria-0.1.0.dist-info/licenses/LICENSE
factoria-0.1.0.dist-info/RECORD
