Metadata-Version: 2.4
Name: factoria
Version: 0.1.0
Summary: A Python library to generate one or more Pydantic models with chainable state modifiers.
License: MIT
License-File: LICENSE
Author: Raphael Ramos
Author-email: raphael.opensource@gmail.com
Requires-Python: >=3.10
Classifier: License :: OSI Approved :: MIT License
Classifier: Programming Language :: Python :: 3
Classifier: Programming Language :: Python :: 3.10
Classifier: Programming Language :: Python :: 3.11
Classifier: Programming Language :: Python :: 3.12
Classifier: Programming Language :: Python :: 3.13
Classifier: Programming Language :: Python :: 3.14
Requires-Dist: pydantic (>=2.0,<3.0)
